[
    {
        "id": 1,
        "icon": {
            "type": "lucide",
            "name": "file-user"
        },
        "text": "Resume",
        "link": "public/assets/Kim_Pham_Resume.pdf"
    },
    {
        "id": 2,
        "icon": {
            "type": "lucide",
            "name": "github"
        },
        "text": "GitHub",
        "link": "https://github.com/kimypham"
    },
    {
        "id": 3,
        "icon": {
            "type": "lucide",
            "name": "linkedin"
        },
        "text": "LinkedIn",
        "link": "https://www.linkedin.com/in/kimypham/"
    },
    {
        "id": 4,
        "icon": {
            "type": "lucide",
            "name": "mail"
        },
        "text": "Email",
        "link": "mailto:km.phm2@gmail.com"
    }
]
